{
    "key": "group_610a81c4be1c9",
    "title": "CPT: Provider Names",
    "fields": [
        {
            "key": "field_610a81c4c4b64",
            "label": "Provider Location",
            "name": "provider_location",
            "type": "relationship",
            "instructions": "",
            "required": 0,
            "conditional_logic": 0,
            "wrapper": {
                "width": "",
                "class": "",
                "id": ""
            },
            "post_type": [
                "provider_locations"
            ],
            "taxonomy": "",
            "filters": [
                "search"
            ],
            "elements": "",
            "min": "",
            "max": "",
            "return_format": "id"
        },
        {
            "key": "field_610a81c4c4bae",
            "label": "First Name",
            "name": "first_name",
            "type": "text",
            "instructions": "",
            "required": 0,
            "conditional_logic": 0,
            "wrapper": {
                "width": "",
                "class": "",
                "id": ""
            },
            "default_value": "",
            "placeholder": "",
            "prepend": "",
            "append": "",
            "maxlength": ""
        },
        {
            "key": "field_610a8249ab3ec",
            "label": "Last Name",
            "name": "last_name",
            "type": "text",
            "instructions": "",
            "required": 0,
            "conditional_logic": 0,
            "wrapper": {
                "width": "",
                "class": "",
                "id": ""
            },
            "default_value": "",
            "placeholder": "",
            "prepend": "",
            "append": "",
            "maxlength": ""
        },
        {
            "key": "field_610bc0cc166c9",
            "label": "National",
            "name": "national",
            "type": "checkbox",
            "instructions": "",
            "required": 0,
            "conditional_logic": 0,
            "wrapper": {
                "width": "",
                "class": "",
                "id": ""
            },
            "choices": {
                "N": "No",
                "Y": "Yes"
            },
            "allow_custom": 0,
            "default_value": [],
            "layout": "vertical",
            "toggle": 0,
            "return_format": "value",
            "save_custom": 0
        },
        {
            "key": "field_610bc102166ca",
            "label": "Select",
            "name": "select",
            "type": "checkbox",
            "instructions": "",
            "required": 0,
            "conditional_logic": 0,
            "wrapper": {
                "width": "",
                "class": "",
                "id": ""
            },
            "choices": {
                "N": "No",
                "Y": "Yes"
            },
            "allow_custom": 0,
            "default_value": [],
            "layout": "vertical",
            "toggle": 0,
            "return_format": "value",
            "save_custom": 0
        },
        {
            "key": "field_610bc119166cc",
            "label": "Hap",
            "name": "hap",
            "type": "checkbox",
            "instructions": "",
            "required": 0,
            "conditional_logic": 0,
            "wrapper": {
                "width": "",
                "class": "",
                "id": ""
            },
            "choices": {
                "N": "No",
                "Y": "Yes"
            },
            "allow_custom": 0,
            "default_value": [],
            "layout": "vertical",
            "toggle": 0,
            "return_format": "value",
            "save_custom": 0
        }
    ],
    "location": [
        [
            {
                "param": "post_type",
                "operator": "==",
                "value": "provider_names"
            }
        ]
    ],
    "menu_order": 0,
    "position": "normal",
    "style": "default",
    "label_placement": "top",
    "instruction_placement": "label",
    "hide_on_screen": "",
    "active": true,
    "description": "",
    "modified": 1628160373
}